alarm_craft/__init__.py
alarm_craft/alarm.py
alarm_craft/cli.py
alarm_craft/config_loader.py
alarm_craft/config_schema.json
alarm_craft/config_schema.py
alarm_craft/core.py
alarm_craft/models.py
alarm_craft/monitoring_targets/__init__.py
alarm_craft/monitoring_targets/facade.py
alarm_craft/monitoring_targets/target_metrics_provider.py
alarm_craft/monitoring_targets/target_metrics_provider_apigw.py
alarm_craft/monitoring_targets/target_metrics_provider_rgta.py
alarm_craft-1.0.1.dist-info/METADATA
alarm_craft-1.0.1.dist-info/WHEEL
alarm_craft-1.0.1.dist-info/entry_points.txt
alarm_craft-1.0.1.dist-info/licenses/LICENSE
alarm_craft-1.0.1.dist-info/RECORD
