Metadata-Version: 2.3
Name: alarm-craft
Version: 1.0.1
Summary: A tool to create AWS CloudWatch Alarms for your resources with specified name and tags
Project-URL: Documentation, https://github.com/alarm-craft/alarm-craft/tree/main?tab=readme-ov-file#readme
Project-URL: Homepage, https://github.com/alarm-craft/alarm-craft
Project-URL: Source, https://github.com/alarm-craft/alarm-craft.git
Project-URL: Issues, https://github.com/alarm-craft/alarm-craft/issues
Project-URL: Changelog, https://github.com/alarm-craft/alarm-craft/blob/main/CHANGELOG.md
Author-email: Ryo Murai <murai.ry@gmail.com>
License-File: LICENSE
Classifier: Development Status :: 5 - Production/Stable
Classifier: Environment :: Console
Classifier: Environment :: Other Environment
Classifier: Intended Audience :: Developers
Classifier: Intended Audience :: Information Technology
Classifier: License :: OSI Approved :: MIT License
Classifier: Operating System :: OS Independent
Classifier: Programming Language :: Python :: 3
Classifier: Topic :: System :: Monitoring
Classifier: Topic :: System :: Systems Administration
Classifier: Topic :: Utilities
Requires-Python: >=3.9
Requires-Dist: boto3==1.34.3
Requires-Dist: botocore==1.34.3
Requires-Dist: jsonschema==4.20.0
Requires-Dist: pyyaml==6.0.1
